pod5_random_access/__init__.py
pod5_random_access/build.py
pod5_random_access/pod5_random_access_pybind.cpython-312-x86_64-linux-gnu.so
pod5_random_access/pod5_random_access_pybind.pyi
pod5_random_access/py.typed
pod5_random_access/reader.py
pod5_random_access/settings.py
pod5_random_access/utils.py
pod5_random_access.libs/libarrow-3fb668e8.so.1200.1.0
pod5_random_access.libs/libbrotlicommon-24c3c480.so.1.0.9
pod5_random_access.libs/libbrotlidec-11aaeb4b.so.1.0.9
pod5_random_access.libs/libbrotlienc-1a6e598f.so.1.0.9
pod5_random_access.libs/libbz2-0be7c010.so.1.0.8
pod5_random_access.libs/libcom_err-c28b3a5a.so.2.1
pod5_random_access.libs/libcrypt-1e9ce68f.so.2.0.0
pod5_random_access.libs/libcrypto-a07a2e9c.so.3.2.2
pod5_random_access.libs/libcurl-997f44d6.so.4.7.0
pod5_random_access.libs/libevent-2-bb9471ec.1.so.7.0.1
pod5_random_access.libs/libgssapi_krb5-82e569d3.so.2.2
pod5_random_access.libs/libidn2-5237fb84.so.0.3.7
pod5_random_access.libs/libk5crypto-188823b6.so.3.1
pod5_random_access.libs/libkeyutils-81e5c457.so.1.10
pod5_random_access.libs/libkrb5-68b134bf.so.3.3
pod5_random_access.libs/libkrb5support-28787768.so.0.1
pod5_random_access.libs/liblber-63bca5a9.so.2.0.200
pod5_random_access.libs/libldap_r-4d1c9e88.so.2.0.200
pod5_random_access.libs/liblz4-9ba322f5.so.1.9.3
pod5_random_access.libs/libnghttp2-25a83100.so.14.20.1
pod5_random_access.libs/libpcre2-8-b77f698a.so.0.11.0
pod5_random_access.libs/libpsl-5e17ba32.so.5.3.3
pod5_random_access.libs/libre2-54877687.so.9.0.0
pod5_random_access.libs/libsasl2-6b2d3aab.so.3.0.0
pod5_random_access.libs/libselinux-a1ff09bf.so.1
pod5_random_access.libs/libsnappy-af7610b7.so.1.1.8
pod5_random_access.libs/libssh-04f53293.so.4.9.4
pod5_random_access.libs/libssl-6942ff50.so.3.2.2
pod5_random_access.libs/libunistring-7ed7589d.so.2.1.0
pod5_random_access.libs/libutf8proc-66071ee1.so.2.4.1
pod5_random_access.libs/libzstd-82d8f7e0.so.1.5.5
pod5_random_access-0.6.0.dist-info/METADATA
pod5_random_access-0.6.0.dist-info/WHEEL
pod5_random_access-0.6.0.dist-info/top_level.txt
pod5_random_access-0.6.0.dist-info/RECORD
pod5_random_access-0.6.0.dist-info/licenses/LICENSE.md
