Metadata-Version: 2.4
Name: pod5-random-access
Version: 0.6.0
Summary: Add your description here
Requires-Python: >=3.10
License-File: LICENSE.md
Requires-Dist: numpy>=2.2.6
Requires-Dist: pyyaml>=6.0.2
Dynamic: license-file
